qWrite/__init__.py
qwrite-0.0.1.dist-info/licenses/LICENSE.txt
qwrite-0.0.1.dist-info/METADATA
qwrite-0.0.1.dist-info/WHEEL
qwrite-0.0.1.dist-info/top_level.txt
qwrite-0.0.1.dist-info/RECORD
